CHANGELOG.md
LICENSE
MANIFEST.in
Makefile
README.md
setup.cfg
setup.py
tox.ini
tests/test_address_formatter.py
tests/test_basic_client.py
tests/test_resolvers.py
tests/test_simple_tree.py
wc_django_geo_db.egg-info/PKG-INFO
wc_django_geo_db.egg-info/SOURCES.txt
wc_django_geo_db.egg-info/dependency_links.txt
wc_django_geo_db.egg-info/requires.txt
wc_django_geo_db.egg-info/top_level.txt
wcd_geo_db/__init__.py
wcd_geo_db/apps.py
wcd_geo_db/client.py
wcd_geo_db/conf.py
wcd_geo_db/const.py
wcd_geo_db/models.py
wcd_geo_db/utils.py
wcd_geo_db/contrib/__init__.py
wcd_geo_db/contrib/admin/__init__.py
wcd_geo_db/contrib/admin/apps.py
wcd_geo_db/contrib/admin/admin/__init__.py
wcd_geo_db/contrib/admin/admin/bank/__init__.py
wcd_geo_db/contrib/admin/admin/bank/divisions.py
wcd_geo_db/contrib/admin/admin/bank/geometry.py
wcd_geo_db/contrib/admin/admin/bank/places.py
wcd_geo_db/contrib/admin/admin/bank/routes.py
wcd_geo_db/contrib/admin/admin/names/__init__.py
wcd_geo_db/contrib/admin/admin/names/divisions.py
wcd_geo_db/contrib/dal/__init__.py
wcd_geo_db/contrib/dal/apps.py
wcd_geo_db/contrib/dal/djhacker.py
wcd_geo_db/contrib/dal/preparators.py
wcd_geo_db/contrib/dal/urls.py
wcd_geo_db/contrib/dal/views.py
wcd_geo_db/contrib/dal/admin/__init__.py
wcd_geo_db/contrib/dal/admin/bank.py
wcd_geo_db/contrib/dal/admin/client.py
wcd_geo_db/contrib/dal/forms/__init__.py
wcd_geo_db/contrib/dal/forms/fields.py
wcd_geo_db/contrib/dal/forms/iterators.py
wcd_geo_db/contrib/dal/forms/widgets.py
wcd_geo_db/management/__init__.py
wcd_geo_db/management/commands/__init__.py
wcd_geo_db/management/commands/wcd_geo_fix_divisions_tree.py
wcd_geo_db/management/commands/wcd_geo_update_labels.py
wcd_geo_db/migrations/0001_initial.py
wcd_geo_db/migrations/0002_auto_20210608_1355.py
wcd_geo_db/migrations/0003_auto_20210610_1042.py
wcd_geo_db/migrations/0004_remove_division_path.py
wcd_geo_db/migrations/0005_rename_path_temp_division_path.py
wcd_geo_db/migrations/0006_division_wcd_geo_db_division_path_index.py
wcd_geo_db/migrations/0007_auto_20210610_1436.py
wcd_geo_db/migrations/0008_auto_20210615_1524.py
wcd_geo_db/migrations/0009_auto_20210616_1837.py
wcd_geo_db/migrations/0010_codes_import_data.py
