Metadata-Version: 2.1
Name: wc-django-geo-db
Version: 0.1.16
Summary: Geographical database for internal projects.
Author: WebCase
Author-email: info@webcase.studio
License: MIT License
Classifier: Development Status :: 2 - Pre-Alpha
Classifier: Programming Language :: Python :: 3
Classifier: Intended Audience :: Developers
Classifier: Topic :: Utilities
Classifier: License :: OSI Approved :: MIT License
Classifier: Operating System :: OS Independent
Requires-Python: >=3.6
Provides-Extra: dev
Provides-Extra: dal
Provides-Extra: sources
License-File: LICENSE
